{
	"name": "functional_if_condition",
	"properties": {
		"activities": [
			{
				"name": "If Condition name",
				"type": "IfCondition",
				"dependsOn": [],
				"userProperties": [],
				"typeProperties": {
					"expression": {
						"value": "@equals(pipeline().parameters.name,'balaji')",
						"type": "Expression"
					},
					"ifFalseActivities": [
						{
							"name": "Wait2",
							"type": "Wait",
							"dependsOn": [],
							"userProperties": [],
							"typeProperties": {
								"waitTimeInSeconds": 3
							}
						}
					],
					"ifTrueActivities": [
						{
							"name": "Wait1",
							"type": "Wait",
							"dependsOn": [],
							"userProperties": [],
							"typeProperties": {
								"waitTimeInSeconds": 5
							}
						}
					]
				}
			},
			{
				"name": "If Condition number",
				"type": "IfCondition",
				"dependsOn": [],
				"userProperties": [],
				"typeProperties": {
					"expression": {
						"value": "@greater(pipeline().parameters.number,10)",
						"type": "Expression"
					},
					"ifFalseActivities": [
						{
							"name": "Wait4",
							"type": "Wait",
							"dependsOn": [],
							"userProperties": [],
							"typeProperties": {
								"waitTimeInSeconds": 5
							}
						}
					],
					"ifTrueActivities": [
						{
							"name": "Wait3",
							"type": "Wait",
							"dependsOn": [],
							"userProperties": [],
							"typeProperties": {
								"waitTimeInSeconds": 3
							}
						}
					]
				}
			}
		],
		"parameters": {
			"name": {
				"type": "string",
				"defaultValue": "sai"
			},
			"number": {
				"type": "int",
				"defaultValue": 3
			}
		},
		"annotations": [],
		"lastPublishTime": "2026-04-05T07:36:24Z"
	},
	"type": "Microsoft.DataFactory/factories/pipelines"
}